icorr/__init__.py
icorr/icorr.py
icorr/plots.py
icorr/stats.py
icorr-0.0.1.dist-info/LICENSE
icorr-0.0.1.dist-info/METADATA
icorr-0.0.1.dist-info/WHEEL
icorr-0.0.1.dist-info/RECORD
