Metadata-Version: 2.1
Name: icorr
Version: 0.0.1
Summary: Identity Correlation Value to measure how identical two arrays X and Y are and how likely this similarity is by random chance.
License: Apache License, Version 2.0
Author: Florian P. Bayer
Author-email: f.bayer@tum.de
Requires-Python: >=3.10,<4.0
Classifier: License :: Other/Proprietary License
Classifier: Programming Language :: Python :: 3
Classifier: Programming Language :: Python :: 3.10
Classifier: Programming Language :: Python :: 3.11
Classifier: Programming Language :: Python :: 3.12
Requires-Dist: matplotlib (==3.6)
Requires-Dist: numpy (>=2.0,<3.0)
Requires-Dist: scipy (>=1.10,<2.0)
